psex/__init__.py
psex/funcs/__init__.py
psex/funcs/assetio.py
psex/pse.py
psex/weaks/__init__.py
psex/weaks/clickhouse.yaml
psex/weaks/elasticsearch.yaml
psex/weaks/mongodb.yaml
psex/weaks/mssql.yaml
psex/weaks/mysql.yaml
psex/weaks/postgresql.yaml
psex/weaks/redis.yaml
psex/weaks/weak_user_pwd.py
psex-0.1.4.dist-info/LICENSE
psex-0.1.4.dist-info/METADATA
psex-0.1.4.dist-info/WHEEL
psex-0.1.4.dist-info/RECORD
