Metadata-Version: 2.1
Name: psex
Version: 0.1.4
Summary: A simple, fast and powerful password scanner engine tool was built by antx.
Home-page: https://github.com/antx-code/psex
License: MIT
Keywords: poc,engine,psex,database,weak password
Author: antx-code
Author-email: wkaifeng2007@163.com
Requires-Python: >=3.8,<4.0
Classifier: License :: OSI Approved :: MIT License
Classifier: Programming Language :: Python :: 3
Classifier: Programming Language :: Python :: 3.8
Classifier: Programming Language :: Python :: 3.9
Classifier: Programming Language :: Python :: 3.10
Classifier: Programming Language :: Python :: 3.11
Requires-Dist: pocx (>=0.2.3,<0.3.0)
Requires-Dist: pyyaml (>=6.0,<7.0)
Project-URL: Repository, https://github.com/antx-code/psex
